smoother/__init__.py
smoother/max_entropy.py
smoother/smoother.py
smoother/utils.py
smoother-0.0.5.dist-info/LICENSE
smoother-0.0.5.dist-info/METADATA
smoother-0.0.5.dist-info/WHEEL
smoother-0.0.5.dist-info/top_level.txt
smoother-0.0.5.dist-info/RECORD
