Metadata-Version: 2.1
Name: smoother
Version: 0.0.5
Summary: Computes non-parametric distributions by optimizing a constrained smoothing function
Home-page: https://github.com/dsbowen/smoother
Author: Dillon Bowen
Author-email: dsbowen@wharton.upenn.edu
License: UNKNOWN
Platform: UNKNOWN
Classifier: Programming Language :: Python :: 3
Classifier: License :: OSI Approved :: MIT License
Classifier: Operating System :: OS Independent
Requires-Python: >=3.6
Requires-Dist: numpy (>=1.19.1)
Requires-Dist: scipy (>=1.5.2)
